whd/VERSION
whd/__init__.py
whd/dispatcher.py
whd/model.py
whd/pipelines.py
whd/pull_request.py
whd/server.py
whd/util.py
whd/webhook.py
gardener_cicd_whd-1.2740.0.dist-info/LICENSE
gardener_cicd_whd-1.2740.0.dist-info/METADATA
gardener_cicd_whd-1.2740.0.dist-info/WHEEL
gardener_cicd_whd-1.2740.0.dist-info/top_level.txt
gardener_cicd_whd-1.2740.0.dist-info/RECORD
