Metadata-Version: 2.1
Name: gardener-cicd-whd
Version: 1.2740.0
Summary: Gardener CI/CD Webhook Dispatcher
Requires-Python: >=3.11
License-File: LICENSE
Requires-Dist: falcon >=2
Requires-Dist: gardener-cicd-cli
Requires-Dist: gardener-cicd-libs
Requires-Dist: uvicorn
Requires-Dist: werkzeug
